pipenv_devcheck/__init__.py
pipenv_devcheck/__main__.py
pipenv_devcheck/__version__.py
pipenv_devcheck/_version.py
pipenv_devcheck/check_fns.py
pipenv_devcheck/pipenv_setup_comp.py
pipenv_devcheck/regexps.py
pipenv_devcheck-0.5.1.dist-info/LICENSE.md
pipenv_devcheck-0.5.1.dist-info/METADATA
pipenv_devcheck-0.5.1.dist-info/WHEEL
pipenv_devcheck-0.5.1.dist-info/entry_points.txt
pipenv_devcheck-0.5.1.dist-info/top_level.txt
pipenv_devcheck-0.5.1.dist-info/RECORD
