Metadata-Version: 2.1
Name: pipenv-devcheck
Version: 0.5.1
Summary: Pipenv/setup.py dependency comparison tool
Home-page: UNKNOWN
Author: George Wood (@Geoiv)
Author-email: george.wood@55places.com
License: MIT
Platform: UNKNOWN
Requires-Dist: packaging (>=20.1)
Requires-Dist: pipfile (>=0.0.2)
